{
"type": "FeatureCollection",
"name": "template",
"crs": { "type": "name", "properties": { "name": "urn:ogc:def:crs:EPSG::3338" } },
"features": [
{ "type": "Feature", "properties": { "WorldID": 156181.0, "CntryID": 6543.0, "Country_Name": "Alaska (US)", "Name_of_Municipality": "Petersburg Census Area", "Name_of_Region": null, "Type_of_Community": "Census Area", "Census_Year": "2012", "Total_Population": 2972.0, "Male_Population": null, "Female_Population": null, "Children_Population": null, "Total_Number_of_Dwellings": null, "Occupied_Dwellings": null, "Origional_Data_Code": null, "Type_of_Area": "Community", "Indiginious_Community": null, "Accessible_via_Roads": null, "Accessible_via_Air": null, "Longitude": -132.957763, "Latitude": 56.8109592, "Relation_to_EN_boundary": "Above", "NEAR_PP_Source": "global_power_plant_database_Alaska", "NEAR_FID_PP": 100.0, "NEAR_DIST_PP": 0.040750080996613355, "NEAR_GridL_Source": "Alaska_Energy_Authority_Library", "NEAR_FID_GridL": 11, "NEAR_DIST_GridL": 0.12885117182600278, "Connection_Type": "Regional grid", "Connection_Type_1": "Connected grid", "Sub_Connection_Type": "Regional grid", "Type_Methods": null, "Name_of_Service_Provider": null, "Power_line_distance": 0.12885117182600278, "Power_plant_distance": 0.040750080996613355, "Transmission_Line_Capacity__kV_": null, "Distribution_Line_Capacity__kV_": null, "Power_line_type": null, "Power_Plant_Name": null, "Power_Plant_Capacity": null, "Power_Plant_Capacity_Revised": null, "Type_of_Power_Plant": null, "Power_Plant_source": null, "Power_plant": null, "Coal_Power_plant": null, "Natural_gas_Power_plant": null, "Oil_Power_plant": null, "Diesel_Power_plant": null, "Nuclear_Power_plant": null, "Small_hydraulic_Power_plant___100_MW_": null, "Large_hydraulic_Power_plant___100_MW_": null, "Solar_Power_plant": null, "Wind_Power_plant": null, "Geothermal_Power_plant": null, "Tidal_Power_plant": null, "Biomass_Power_plant": null, "Combined_Heat_Power_Plant__CHPP_": null, "Hybrid_Power_plants": null, "Total_Power_Plant": null, "Total_Energy_Capacity": null, "Total_Renewable_Energy_Capacity": null, "Total_Nonrenewable_Energy_Capacity": null, "Total_Energy_generation": null, "Total_Renewable_Energy_generation": null, "Total_Nonrenewable_Energy_generation": null, "Renewable_Percent": null, "Nonrenewable_Percent": null, "Annual_Energy_demand": null, "Community_energy_plan": null, "Primary_Fuel": null, "Owner_Name": null, "Check_Need": null, "Pop_Difference_Borough": null, "Missing_Name": null, "Check_Result": null, "Comment_GRL": null, "Note": null, "Name_of_Settlement": "Petersburg", "Remote_Community_PP_FID": null, "Remote_Community_PP_Type": null, "Remote_Community_PP_Capacity": null, "Remote_Community_PP_Owner": null }, "geometry": { "type": "Point", "coordinates": [ 1261269.797844427637756, 957469.307257314911112 ] } }
]
}
